README.rst
setup.py
comk_django_account/__init__.py
comk_django_account/account_conf.py
comk_django_account/admin.py
comk_django_account/apps.py
comk_django_account/urls.py
comk_django_account.egg-info/PKG-INFO
comk_django_account.egg-info/SOURCES.txt
comk_django_account.egg-info/dependency_links.txt
comk_django_account.egg-info/requires.txt
comk_django_account.egg-info/top_level.txt
comk_django_account/migrations/0001_initial.py
comk_django_account/migrations/__init__.py
comk_django_account/models/Account.py
comk_django_account/models/AccountUseInfo.py
comk_django_account/models/__init__.py
comk_django_account/tests/__init__.py
comk_django_account/tests/test_API.py
comk_django_account/tests/test_model.py
comk_django_account/views/AcountView.py
comk_django_account/views/Funs.py
comk_django_account/views/__init__.py
comk_django_account/views/dao/AccountDao.py
comk_django_account/views/dao/__init__.py
comk_django_account/views/service/AddAcountServer.py
comk_django_account/views/service/__init__.py
comk_django_account/views/utils/__init__.py
comk_django_account/views/utils/app_check.py
comk_django_account/views/utils/cache_utils.py
comk_django_account/views/utils/params_utils.py
comk_django_account/views/utils/sign_utils.py