Metadata-Version: 1.2
Name: comk-django-account
Version: 1.0.5
Summary: comk个人开发的account模型，用于构建RSA-SHA256验证的权限系统
Home-page: UNKNOWN
Author: comk
Author-email: 1943336161@qq.com
Maintainer: comk
Maintainer-email: 1943336161@qq.com
License: BSD License
Platform: all
Classifier: Development Status :: 4 - Beta
Classifier: Operating System :: OS Independent
Classifier: Intended Audience :: Developers
Classifier: License :: OSI Approved :: BSD License
Classifier: Programming Language :: Python
Classifier: Programming Language :: Python :: Implementation
Classifier: Programming Language :: Python :: 3
Classifier: Programming Language :: Python :: 3.4
Classifier: Programming Language :: Python :: 3.5
Classifier: Programming Language :: Python :: 3.6
Classifier: Topic :: Software Development :: Libraries
